MANIFEST.in
setup.py
django_technology_radar.egg-info/PKG-INFO
django_technology_radar.egg-info/SOURCES.txt
django_technology_radar.egg-info/dependency_links.txt
django_technology_radar.egg-info/requires.txt
django_technology_radar.egg-info/top_level.txt
technology_radar/__init__.py
technology_radar/admin.py
technology_radar/apps.py
technology_radar/models.py
technology_radar/renderers.py
technology_radar/urls.py
technology_radar/utils.py
technology_radar/fixtures/radar.json
technology_radar/migrations/0001_initial.py
technology_radar/migrations/0002_auto_20160212_1603.py
technology_radar/migrations/__init__.py
technology_radar/serializers/__init__.py
technology_radar/serializers/radar.py
technology_radar/templates/technology_radar/area.html
technology_radar/templates/technology_radar/blip.html
technology_radar/templates/technology_radar/index.html
technology_radar/templates/technology_radar/radar.html
technology_radar/templatetags/__init__.py
technology_radar/templatetags/technology_radar_tags.py
technology_radar/tests/__init__.py
technology_radar/tests/test_radar.py
technology_radar/tests/test_root.py
technology_radar/tests/test_utils.py
technology_radar/tests/factories/__init__.py
technology_radar/tests/factories/radar.py
technology_radar/views/__init__.py
technology_radar/views/api.py
technology_radar/views/radar.py
technology_radar/views/root.py