Metadata-Version: 1.1
Name: django-technology-radar
Version: 0.1.0
Summary: A Django app for building your own Technology Radar.
Home-page: https://github.com/moorinteractive/django-technology-radar
Author: Rob Moorman
Author-email: rob@moori.nl
License: UNKNOWN
Download-URL: https://github.com/moorinteractive/django-technology-radar/tarball/0.1.0
Platform: UNKNOWN
